probconcept/__init__.py
probconcept/probconcept.py
probconcept/py.typed
probconcept/version.py
probconcept-0.1.0.dist-info/LICENSE
probconcept-0.1.0.dist-info/METADATA
probconcept-0.1.0.dist-info/WHEEL
probconcept-0.1.0.dist-info/top_level.txt
probconcept-0.1.0.dist-info/RECORD
