Metadata-Version: 2.1
Name: probconcept
Version: 0.1.0
Author-email: "Frank L. Engel" <fengel@usgs.gov>
License: Attribution 4.0 International
Project-URL: Homepage, https://github.com/frank-engel-usgs/probconcept
Project-URL: Repository, https://github.com/frank-engel-usgs/probconcept
Project-URL: Changelog, https://github.com/frank-engel-usgs/probconcept/blob/main/CHANGELOG.md
Keywords: probability concept,hydraulics,river,open channel hydrualics
Classifier: Intended Audience :: Science/Research
Classifier: Development Status :: 3 - Alpha
Classifier: License :: OSI Approved :: Apache Software License
Classifier: Programming Language :: Python :: 3
Classifier: Topic :: Scientific/Engineering :: Artificial Intelligence
Requires-Python: >=3.9
License-File: LICENSE
Requires-Dist: numpy >=1.26.2
Requires-Dist: lmfit >=1.2.2
Requires-Dist: pybroom >=0.2
Requires-Dist: scipy >=1.11.4
Requires-Dist: pandas >=2.1.4
Provides-Extra: dev
Requires-Dist: ruff ; extra == 'dev'
Requires-Dist: mypy <1.5,>=1.0 ; extra == 'dev'
Requires-Dist: black <24.0,>=23.0 ; extra == 'dev'
Requires-Dist: isort <5.13,>=5.12 ; extra == 'dev'
Requires-Dist: pytest ; extra == 'dev'
Requires-Dist: pytest-sphinx ; extra == 'dev'
Requires-Dist: pytest-cov ; extra == 'dev'
Requires-Dist: twine >=1.11.0 ; extra == 'dev'
Requires-Dist: build ; extra == 'dev'
Requires-Dist: setuptools ; extra == 'dev'
Requires-Dist: wheel ; extra == 'dev'
Requires-Dist: Sphinx <7.1.0,>=4.3.0 ; extra == 'dev'
Requires-Dist: furo ==2023.7.26 ; extra == 'dev'
Requires-Dist: myst-parser <2.1,>=1.0 ; extra == 'dev'
Requires-Dist: sphinx-copybutton ==0.5.2 ; extra == 'dev'
Requires-Dist: sphinx-autobuild ==2021.3.14 ; extra == 'dev'
Requires-Dist: sphinx-autodoc-typehints ==1.23.3 ; extra == 'dev'
Requires-Dist: packaging ; extra == 'dev'
